odoo8_addon_purchase_procurement_analytic-8.0.1.0.0.99.dev22-py3.8-nspkg.pth
odoo_addons/purchase_procurement_analytic/README.rst
odoo_addons/purchase_procurement_analytic/__init__.py
odoo_addons/purchase_procurement_analytic/__openerp__.py
odoo_addons/purchase_procurement_analytic/i18n/ca.po
odoo_addons/purchase_procurement_analytic/i18n/cs_CZ.po
odoo_addons/purchase_procurement_analytic/i18n/de.po
odoo_addons/purchase_procurement_analytic/i18n/es.po
odoo_addons/purchase_procurement_analytic/i18n/es_AR.po
odoo_addons/purchase_procurement_analytic/i18n/es_MX.po
odoo_addons/purchase_procurement_analytic/i18n/es_PE.po
odoo_addons/purchase_procurement_analytic/i18n/fi.po
odoo_addons/purchase_procurement_analytic/i18n/fr.po
odoo_addons/purchase_procurement_analytic/i18n/hr.po
odoo_addons/purchase_procurement_analytic/i18n/it.po
odoo_addons/purchase_procurement_analytic/i18n/nl_NL.po
odoo_addons/purchase_procurement_analytic/i18n/pt.po
odoo_addons/purchase_procurement_analytic/i18n/pt_BR.po
odoo_addons/purchase_procurement_analytic/i18n/pt_PT.po
odoo_addons/purchase_procurement_analytic/i18n/purchase_procurement_analytic.pot
odoo_addons/purchase_procurement_analytic/i18n/ro.po
odoo_addons/purchase_procurement_analytic/i18n/sk.po
odoo_addons/purchase_procurement_analytic/i18n/sl.po
odoo_addons/purchase_procurement_analytic/i18n/tr.po
odoo_addons/purchase_procurement_analytic/i18n/tr_TR.po
odoo_addons/purchase_procurement_analytic/i18n/zh_CN.po
odoo_addons/purchase_procurement_analytic/models/__init__.py
odoo_addons/purchase_procurement_analytic/models/procurement.py
odoo_addons/purchase_procurement_analytic/models/purchase.py
odoo_addons/purchase_procurement_analytic/models/stock.py
odoo_addons/purchase_procurement_analytic/static/description/icon.png
odoo_addons/purchase_procurement_analytic/tests/__init__.py
odoo_addons/purchase_procurement_analytic/tests/test_purchase_procurement_analytic.py
odoo8_addon_purchase_procurement_analytic-8.0.1.0.0.99.dev22.dist-info/METADATA
odoo8_addon_purchase_procurement_analytic-8.0.1.0.0.99.dev22.dist-info/WHEEL
odoo8_addon_purchase_procurement_analytic-8.0.1.0.0.99.dev22.dist-info/namespace_packages.txt
odoo8_addon_purchase_procurement_analytic-8.0.1.0.0.99.dev22.dist-info/top_level.txt
odoo8_addon_purchase_procurement_analytic-8.0.1.0.0.99.dev22.dist-info/RECORD
